{"content": {"activities": [{"version": 2, "type": "sleep", "start_time": {"timestamp": 1454378920, "iso": "2016-02-02T02:08:40Z", "time_zone": {"name": "Europe/Copenhagen", "offset": 60}}, "calories": 340.79998779296875, "actual_seconds": 15720, "id": "sleep__2016-02-02T020840", "state": "complete", "heart_rate": {"max": null, "avg": 54.43483352661133, "min": null}, "sleep": {"unknown_minutes": 6, "light_percent": 56.10687022900763, "quality": 93, "unknown_percent": 2.2900763358778624, "interruption_minutes": 0, "rem_minutes": 60, "light_minutes": 147, "deep_minutes": 49, "rem_percent": 22.900763358778626, "interruptions": 0, "deep_percent": 18.702290076335878, "toss_and_turn": 25}, "end_time": {"timestamp": 1454394687, "iso": "2016-02-02T06:31:27Z", "time_zone": {"name": "Europe/Copenhagen", "offset": 60}}, "sealed": true, "date": "2016-02-01", "stages": [{"type": "light", "start_time": {"timestamp": 1454378940, "iso": "2016-02-02T02:09:00Z", "time_zone": {"name": "Europe/Copenhagen", "offset": 60}}, "minutes": 22, "end_time": {"timestamp": 1454380260, "iso": "2016-02-02T02:31:00Z", "time_zone": {"name": "Europe/Copenhagen", "offset": 60}}}, {"type": "deep", "start_time": {"timestamp": 1454380260, "iso": "2016-02-02T02:31:00Z", "time_zone": {"name": "Europe/Copenhagen", "offset": 60}}, "minutes": 6, "end_time": {"timestamp": 1454380620, "iso": "2016-02-02T02:37:00Z", "time_zone": {"name": "Europe/Copenhagen", "offset": 60}}}, {"type": "light", "start_time": {"timestamp": 1454380620, "iso": "2016-02-02T02:37:00Z", "time_zone": {"name": "Europe/Copenhagen", "offset": 60}}, "minutes": 12, "end_time": {"timestamp": 1454381340, "iso": "2016-02-02T02:49:00Z", "time_zone": {"name": "Europe/Copenhagen", "offset": 60}}}, {"type": "rem", "start_time": {"timestamp": 1454381340, "iso": "2016-02-02T02:49:00Z", "time_zone": {"name": "Europe/Copenhagen", "offset": 60}}, "minutes": 14, "end_time": {"timestamp": 1454382180, "iso": "2016-02-02T03:03:00Z", "time_zone": {"name": "Europe/Copenhagen", "offset": 60}}}, {"type": "light", "start_time": {"timestamp": 1454382180, "iso": "2016-02-02T03:03:00Z", "time_zone": {"name": "Europe/Copenhagen", "offset": 60}}, "minutes": 1, "end_time": {"timestamp": 1454382240, "iso": "2016-02-02T03:04:00Z", "time_zone": {"name": "Europe/Copenhagen", "offset": 60}}}, {"type": "deep", "start_time": {"timestamp": 1454382240, "iso": "2016-02-02T03:04:00Z", "time_zone": {"name": "Europe/Copenhagen", "offset": 60}}, "minutes": 26, "end_time": {"timestamp": 1454383800, "iso": "2016-02-02T03:30:00Z", "time_zone": {"name": "Europe/Copenhagen", "offset": 60}}}, {"type": "light", "start_time": {"timestamp": 1454383800, "iso": "2016-02-02T03:30:00Z", "time_zone": {"name": "Europe/Copenhagen", "offset": 60}}, "minutes": 21, "end_time": {"timestamp": 1454385060, "iso": "2016-02-02T03:51:00Z", "time_zone": {"name": "Europe/Copenhagen", "offset": 60}}}, {"type": "rem", "start_time": {"timestamp": 1454385060, "iso": "2016-02-02T03:51:00Z", "time_zone": {"name": "Europe/Copenhagen", "offset": 60}}, "minutes": 24, "end_time": {"timestamp": 1454386500, "iso": "2016-02-02T04:15:00Z", "time_zone": {"name": "Europe/Copenhagen", "offset": 60}}}, {"type": "light", "start_time": {"timestamp": 1454386500, "iso": "2016-02-02T04:15:00Z", "time_zone": {"name": "Europe/Copenhagen", "offset": 60}}, "minutes": 39, "end_time": {"timestamp": 1454388840, "iso": "2016-02-02T04:54:00Z", "time_zone": {"name": "Europe/Copenhagen", "offset": 60}}}, {"type": "deep", "start_time": {"timestamp": 1454388840, "iso": "2016-02-02T04:54:00Z", "time_zone": {"name": "Europe/Copenhagen", "offset": 60}}, "minutes": 8, "end_time": {"timestamp": 1454389320, "iso": "2016-02-02T05:02:00Z", "time_zone": {"name": "Europe/Copenhagen", "offset": 60}}}, {"type": "light", "start_time": {"timestamp": 1454389320, "iso": "2016-02-02T05:02:00Z", "time_zone": {"name": "Europe/Copenhagen", "offset": 60}}, "minutes": 19, "end_time": {"timestamp": 1454390460, "iso": "2016-02-02T05:21:00Z", "time_zone": {"name": "Europe/Copenhagen", "offset": 60}}}, {"type": "deep", "start_time": {"timestamp": 1454390460, "iso": "2016-02-02T05:21:00Z", "time_zone": {"name": "Europe/Copenhagen", "offset": 60}}, "minutes": 9, "end_time": {"timestamp": 1454391000, "iso": "2016-02-02T05:30:00Z", "time_zone": {"name": "Europe/Copenhagen", "offset": 60}}}, {"type": "light", "start_time": {"timestamp": 1454391000, "iso": "2016-02-02T05:30:00Z", "time_zone": {"name": "Europe/Copenhagen", "offset": 60}}, "minutes": 11, "end_time": {"timestamp": 1454391660, "iso": "2016-02-02T05:41:00Z", "time_zone": {"name": "Europe/Copenhagen", "offset": 60}}}, {"type": "rem", "start_time": {"timestamp": 1454391660, "iso": "2016-02-02T05:41:00Z", "time_zone": {"name": "Europe/Copenhagen", "offset": 60}}, "minutes": 3, "end_time": {"timestamp": 1454391840, "iso": "2016-02-02T05:44:00Z", "time_zone": {"name": "Europe/Copenhagen", "offset": 60}}}, {"type": "unknown", "start_time": {"timestamp": 1454391840, "iso": "2016-02-02T05:44:00Z", "time_zone": {"name": "Europe/Copenhagen", "offset": 60}}, "minutes": 6, "end_time": {"timestamp": 1454392200, "iso": "2016-02-02T05:50:00Z", "time_zone": {"name": "Europe/Copenhagen", "offset": 60}}}, {"type": "rem", "start_time": {"timestamp": 1454392200, "iso": "2016-02-02T05:50:00Z", "time_zone": {"name": "Europe/Copenhagen", "offset": 60}}, "minutes": 1, "end_time": {"timestamp": 1454392260, "iso": "2016-02-02T05:51:00Z", "time_zone": {"name": "Europe/Copenhagen", "offset": 60}}}, {"type": "light", "start_time": {"timestamp": 1454392260, "iso": "2016-02-02T05:51:00Z", "time_zone": {"name": "Europe/Copenhagen", "offset": 60}}, "minutes": 21, "end_time": {"timestamp": 1454393520, "iso": "2016-02-02T06:12:00Z", "time_zone": {"name": "Europe/Copenhagen", "offset": 60}}}, {"type": "rem", "start_time": {"timestamp": 1454393520, "iso": "2016-02-02T06:12:00Z", "time_zone": {"name": "Europe/Copenhagen", "offset": 60}}, "minutes": 18, "end_time": {"timestamp": 1454394600, "iso": "2016-02-02T06:30:00Z", "time_zone": {"name": "Europe/Copenhagen", "offset": 60}}}, {"type": "light", "start_time": {"timestamp": 1454394600, "iso": "2016-02-02T06:30:00Z", "time_zone": {"name": "Europe/Copenhagen", "offset": 60}}, "minutes": 1, "end_time": {"timestamp": 1454394660, "iso": "2016-02-02T06:31:00Z", "time_zone": {"name": "Europe/Copenhagen", "offset": 60}}}], "minutes": 262, "events": [{"type": "toss_and_turn", "time": {"timestamp": 1454378940, "iso": "2016-02-02T02:09:00Z", "time_zone": {"name": "Europe/Copenhagen", "offset": 60}}}, {"type": "toss_and_turn", "time": {"timestamp": 1454379120, "iso": "2016-02-02T02:12:00Z", "time_zone": {"name": "Europe/Copenhagen", "offset": 60}}}, {"type": "toss_and_turn", "time": {"timestamp": 1454380380, "iso": "2016-02-02T02:33:00Z", "time_zone": {"name": "Europe/Copenhagen", "offset": 60}}}, {"type": "toss_and_turn", "time": {"timestamp": 1454380620, "iso": "2016-02-02T02:37:00Z", "time_zone": {"name": "Europe/Copenhagen", "offset": 60}}}, {"type": "toss_and_turn", "time": {"timestamp": 1454380680, "iso": "2016-02-02T02:38:00Z", "time_zone": {"name": "Europe/Copenhagen", "offset": 60}}}, {"type": "toss_and_turn", "time": {"timestamp": 1454381880, "iso": "2016-02-02T02:58:00Z", "time_zone": {"name": "Europe/Copenhagen", "offset": 60}}}, {"type": "toss_and_turn", "time": {"timestamp": 1454384100, "iso": "2016-02-02T03:35:00Z", "time_zone": {"name": "Europe/Copenhagen", "offset": 60}}}, {"type": "toss_and_turn", "time": {"timestamp": 1454384520, "iso": "2016-02-02T03:42:00Z", "time_zone": {"name": "Europe/Copenhagen", "offset": 60}}}, {"type": "toss_and_turn", "time": {"timestamp": 1454385060, "iso": "2016-02-02T03:51:00Z", "time_zone": {"name": "Europe/Copenhagen", "offset": 60}}}, {"type": "toss_and_turn", "time": {"timestamp": 1454385420, "iso": "2016-02-02T03:57:00Z", "time_zone": {"name": "Europe/Copenhagen", "offset": 60}}}, {"type": "toss_and_turn", "time": {"timestamp": 1454387340, "iso": "2016-02-02T04:29:00Z", "time_zone": {"name": "Europe/Copenhagen", "offset": 60}}}, {"type": "toss_and_turn", "time": {"timestamp": 1454387640, "iso": "2016-02-02T04:34:00Z", "time_zone": {"name": "Europe/Copenhagen", "offset": 60}}}, {"type": "toss_and_turn", "time": {"timestamp": 1454387700, "iso": "2016-02-02T04:35:00Z", "time_zone": {"name": "Europe/Copenhagen", "offset": 60}}}, {"type": "toss_and_turn", "time": {"timestamp": 1454387880, "iso": "2016-02-02T04:38:00Z", "time_zone": {"name": "Europe/Copenhagen", "offset": 60}}}, {"type": "toss_and_turn", "time": {"timestamp": 1454388600, "iso": "2016-02-02T04:50:00Z", "time_zone": {"name": "Europe/Copenhagen", "offset": 60}}}, {"type": "toss_and_turn", "time": {"timestamp": 1454389980, "iso": "2016-02-02T05:13:00Z", "time_zone": {"name": "Europe/Copenhagen", "offset": 60}}}, {"type": "toss_and_turn", "time": {"timestamp": 1454390460, "iso": "2016-02-02T05:21:00Z", "time_zone": {"name": "Europe/Copenhagen", "offset": 60}}}, {"type": "toss_and_turn", "time": {"timestamp": 1454391540, "iso": "2016-02-02T05:39:00Z", "time_zone": {"name": "Europe/Copenhagen", "offset": 60}}}, {"type": "toss_and_turn", "time": {"timestamp": 1454392260, "iso": "2016-02-02T05:51:00Z", "time_zone": {"name": "Europe/Copenhagen", "offset": 60}}}, {"type": "toss_and_turn", "time": {"timestamp": 1454392620, "iso": "2016-02-02T05:57:00Z", "time_zone": {"name": "Europe/Copenhagen", "offset": 60}}}, {"type": "toss_and_turn", "time": {"timestamp": 1454393280, "iso": "2016-02-02T06:08:00Z", "time_zone": {"name": "Europe/Copenhagen", "offset": 60}}}, {"type": "toss_and_turn", "time": {"timestamp": 1454393520, "iso": "2016-02-02T06:12:00Z", "time_zone": {"name": "Europe/Copenhagen", "offset": 60}}}, {"type": "toss_and_turn", "time": {"timestamp": 1454393580, "iso": "2016-02-02T06:13:00Z", "time_zone": {"name": "Europe/Copenhagen", "offset": 60}}}, {"type": "toss_and_turn", "time": {"timestamp": 1454394480, "iso": "2016-02-02T06:28:00Z", "time_zone": {"name": "Europe/Copenhagen", "offset": 60}}}, {"type": "toss_and_turn", "time": {"timestamp": 1454394660, "iso": "2016-02-02T06:31:00Z", "time_zone": {"name": "Europe/Copenhagen", "offset": 60}}}]}]}, "meta": {"response_code": 200}}